{
  "ConquestLarge0": "Conquest Large",
  "ConquestAssaultLarge0": "Assault Large",
  "ConquestSmall0": "Conquest",
  "ConquestAssaultSmall0": "Assault",
  "ConquestAssaultSmall1": "Assault 2",
  "RushLarge0": "Rush",
  "SquadRush0": "Squad Rush",
  "SquadDeathMatch0": "Squad Deathmatch",
  "TeamDeathMatch0": "Team Deathmatch",
  "TeamDeathMatchC0": "TDM Close Quarters",
  "GunMaster0": "Gun Master",
  "Domination0": "Conquest Domination",
  "TankSuperiority0": "Tank Superiority",
  "Scavenger0": "Scavenger",
  "CaptureTheFlag0": "Capture The Flag",
  "AirSuperiority0": "Air Superiority"
}
